fashion/__init__.py
fashion/databaseAccess.py
fashion/fashionCmds.py
fashion/mirror.py
fashion/modelAccess.py
fashion/portfolio.py
fashion/runway.py
fashion/schema.py
fashion/segment.py
fashion/util.py
fashion/warehouse.py
fashion/xforms.py
fashionModel-0.2.0.dev1.dist-info/LICENSE.txt
fashionModel-0.2.0.dev1.dist-info/METADATA
fashionModel-0.2.0.dev1.dist-info/WHEEL
fashionModel-0.2.0.dev1.dist-info/entry_points.txt
fashionModel-0.2.0.dev1.dist-info/top_level.txt
fashionModel-0.2.0.dev1.dist-info/RECORD
