Metadata-Version: 2.1
Name: fashionModel
Version: 0.2.0.dev1
Summary: A utility for simple model transformation and source code generation
Home-page: https://github.com/braddillman/fashion
Author: Brad Dillman
Author-email: braddillman@gmail.com
License: License :: OSI Approved :: Apache Software License
Requires-Dist: tinydb (==3.12.2)
Requires-Dist: munch (==2.3.2)
Requires-Dist: jsonschema (==2.6.0)
Requires-Dist: genson (==1.0.2)
Requires-Dist: xmltodict (==0.11.0)
Requires-Dist: Jinja2 (==2.10)
Provides-Extra: dev
Requires-Dist: check-manifest ; extra == 'dev'
Requires-Dist: pylint ; extra == 'dev'
Provides-Extra: test
Requires-Dist: coverage ; extra == 'test'
Requires-Dist: pytest ; extra == 'test'
